Epiverse/__init__.py
Epiverse/Concat/__init__.py
Epiverse/Concat/_concat.py
Epiverse/ScRNA/__init__.py
Epiverse/ScRNA/_pyscenic.py
Epiverse/pl/__init__.py
Epiverse/pp/__init__.py
Epiverse/pp/_scATAC_qc.py
Epiverse/utils/__init__.py
Epiverse/utils/_data.py
Epiverse/utils/_read.py
epiverse-0.0.1.dist-info/LICENSE
epiverse-0.0.1.dist-info/WHEEL
epiverse-0.0.1.dist-info/METADATA
epiverse-0.0.1.dist-info/RECORD
